splitraster/__init__.py
splitraster/geo.py
splitraster/io.py
splitraster-0.3.7.dist-info/LICENSE
splitraster-0.3.7.dist-info/METADATA
splitraster-0.3.7.dist-info/WHEEL
splitraster-0.3.7.dist-info/top_level.txt
splitraster-0.3.7.dist-info/RECORD
