Metadata-Version: 2.1
Name: splitraster
Version: 0.3.7
Summary: Provide good support for deep learning and computer vision tasks by creating a tiled output from an input raster dataset.
Home-page: https://github.com/cuicaihao/split_raster
Author: Chris Cui
Author-email: 
License: MIT
Keywords: split raster tiling
Platform: any
Classifier: License :: OSI Approved :: MIT License
Classifier: Operating System :: OS Independent
Classifier: Programming Language :: Python :: 3.7
Classifier: Programming Language :: Python :: 3.8
Classifier: Programming Language :: Python :: 3.9
Classifier: Programming Language :: Python :: 3.10
Classifier: Programming Language :: Python :: 3.11
Classifier: Programming Language :: Python :: 3.12
Classifier: Programming Language :: Python :: 3.13
Requires-Python: >=3.7, <3.14
License-File: LICENSE
Requires-Dist: numpy<2.0.0,>=1.19.0
Requires-Dist: tqdm<5.0.0,>=4.40.0
Requires-Dist: scikit-image<1.0.0,>=0.18.0
